Workbook

Sheet Sales_Data
A1: Order_ID | B1: Date | C1: Month | D1: City | E1: Category | F1: Product | G1: Salesperson | H1: Quantity | I1: Unit_Price_PKR | J1: Discount_% | K1: Revenue_PKR | L1: Cost_PKR | M1: Profit_PKR
A2: ORD-1001 | B2: 45720 | C2: March | D2: Lahore | E2: Groceries | F2: Desi Ghee | G2: Ayesha Malik | H2: 5 | I2: 1800 | J2: 0 | K2: =H2*I2*(1-J2/100) -> 9000 | L2: =K2*0.69 -> 6210 | M2: =K2-L2 -> 2790
A3: ORD-1002 | B3: 45719 | C3: March | D3: Rawalpindi | E3: Furniture | F3: Sofa Set | G3: Ahmed Ali | H3: 3 | I3: 85000 | J3: 5 | K3: =H3*I3*(1-J3/100) -> 242250 | L3: =K3*0.6 -> 145350 | M3: =K3-L3 -> 96900
A4: ORD-1003 | B4: 45717 | C4: March | D4: Rawalpindi | E4: Electronics | F4: Smart Watch | G4: Zain Hussain | H4: 8 | I4: 22000 | J4: 15 | K4: =H4*I4*(1-J4/100) -> 149600 | L4: =K4*0.67 -> 100232 | M4: =K4-L4 -> 49368
A5: ORD-1004 | B5: 45682 | C5: January | D5: Karachi | E5: Furniture | F5: Wardrobe | G5: Bilal Sheikh | H5: 5 | I5: 62000 | J5: 5 | K5: =H5*I5*(1-J5/100) -> 294500 | L5: =K5*0.74 -> 217930 | M5: =K5-L5 -> 76570
A6: ORD-1005 | B6: 45692 | C6: February | D6: Lahore | E6: Furniture | F6: Sofa Set | G6: Sana Iqbal | H6: 12 | I6: 85000 | J6: 20 | K6: =H6*I6*(1-J6/100) -> 816000 | L6: =K6*0.6 -> 489600 | M6: =K6-L6 -> 326400
A7: ORD-1006 | B7: 45681 | C7: January | D7: Faisalabad | E7: Cosmetics | F7: Skin Cream | G7: Zain Hussain | H7: 3 | I7: 1200 | J7: 20 | K7: =H7*I7*(1-J7/100) -> 2880 | L7: =K7*0.61 -> 1756.8 | M7: =K7-L7 -> 1123.2
A8: ORD-1007 | B8: 45736 | C8: March | D8: Islamabad | E8: Cosmetics | F8: Lipstick | G8: Fatima Khan | H8: 2 | I8: 800 | J8: 5 | K8: =H8*I8*(1-J8/100) -> 1520 | L8: =K8*0.7 -> 1064 | M8: =K8-L8 -> 456
A9: ORD-1008 | B9: 45685 | C9: January | D9: Karachi | E9: Clothing | F9: T-Shirt | G9: Bilal Sheikh | H9: 15 | I9: 900 | J9: 10 | K9: =H9*I9*(1-J9/100) -> 12150 | L9: =K9*0.58 -> 7047 | M9: =K9-L9 -> 5103
A10: ORD-1009 | B10: 45695 | C10: February | D10: Islamabad | E10: Clothing | F10: Dupatta | G10: Usman Raza | H10: 18 | I10: 700 | J10: 5 | K10: =H10*I10*(1-J10/100) -> 11970 | L10: =K10*0.58 -> 6942.6 | M10: =K10-L10 -> 5027.4
A11: ORD-1010 | B11: 45697 | C11: February | D11: Rawalpindi | E11: Electronics | F11: Headphones | G11: Ahmed Ali | H11: 8 | I11: 8500 | J11: 0 | K11: =H11*I11*(1-J11/100) -> 68000 | L11: =K11*0.71 -> 48280 | M11: =K11-L11 -> 19720
A12: ORD-1011 | B12: 45697 | C12: February | D12: Lahore | E12: Electronics | F12: Smart Watch | G12: Sana Iqbal | H12: 7 | I12: 22000 | J12: 15 | K12: =H12*I12*(1-J12/100) -> 130900 | L12: =K12*0.63 -> 82467 | M12: =K12-L12 -> 48433
A13: ORD-1012 | B13: 45731 | C13: March | D13: Karachi | E13: Groceries | F13: Desi Ghee | G13: Ayesha Malik | H13: 18 | I13: 1800 | J13: 20 | K13: =H13*I13*(1-J13/100) -> 25920 | L13: =K13*0.6 -> 15552 | M13: =K13-L13 -> 10368
A14: ORD-1013 | B14: 45730 | C14: March | D14: Rawalpindi | E14: Furniture | F14: Wardrobe | G14: Ayesha Malik | H14: 5 | I14: 62000 | J14: 20 | K14: =H14*I14*(1-J14/100) -> 248000 | L14: =K14*0.65 -> 161200 | M14: =K14-L14 -> 86800
A15: ORD-1014 | B15: 45685 | C15: January | D15: Lahore | E15: Electronics | F15: Laptop | G15: Zain Hussain | H15: 20 | I15: 120000 | J15: 0 | K15: =H15*I15*(1-J15/100) -> 2400000 | L15: =K15*0.63 -> 1512000 | M15: =K15-L15 -> 888000
A16: ORD-1015 | B16: 45731 | C16: March | D16: Rawalpindi | E16: Groceries | F16: Sugar | G16: Ahmed Ali | H16: 4 | I16: 200 | J16: 20 | K16: =H16*I16*(1-J16/100) -> 640 | L16: =K16*0.7 -> 448 | M16: =K16-L16 -> 192
A17: ORD-1016 | B17: 45727 | C17: March | D17: Lahore | E17: Groceries | F17: Cooking Oil | G17: Usman Raza | H17: 15 | I17: 650 | J17: 0 | K17: =H17*I17*(1-J17/100) -> 9750 | L17: =K17*0.74 -> 7215 | M17: =K17-L17 -> 2535
A18: ORD-1017 | B18: 45725 | C18: March | D18: Rawalpindi | E18: Electronics | F18: Smart Watch | G18: Fatima Khan | H18: 10 | I18: 22000 | J18: 20 | K18: =H18*I18*(1-J18/100) -> 176000 | L18: =K18*0.67 -> 117920 | M18: =K18-L18 -> 58080
A19: ORD-1018 | B19: 45669 | C19: January | D19: Karachi | E19: Cosmetics | F19: Face Wash | G19: Ahmed Ali | H19: 20 | I19: 450 | J19: 10 | K19: =H19*I19*(1-J19/100) -> 8100 | L19: =K19*0.65 -> 5265 | M19: =K19-L19 -> 2835
A20: ORD-1019 | B20: 45669 | C20: January | D20: Islamabad | E20: Electronics | F20: Mobile Phone | G20: Ayesha Malik | H20: 19 | I20: 45000 | J20: 0 | K20: =H20*I20*(1-J20/100) -> 855000 | L20: =K20*0.57 -> 487350 | M20: =K20-L20 -> 367650
A21: ORD-1020 | B21: 45715 | C21: February | D21: Lahore | E21: Cosmetics | F21: Lipstick | G21: Usman Raza | H21: 16 | I21: 800 | J21: 20 | K21: =H21*I21*(1-J21/100) -> 10240 | L21: =K21*0.58 -> 5939.2 | M21: =K21-L21 -> 4300.8
A22: ORD-1021 | B22: 45744 | C22: March | D22: Rawalpindi | E22: Furniture | F22: Dining Table | G22: Kamran Butt | H22: 7 | I22: 45000 | J22: 10 | K22: =H22*I22*(1-J22/100) -> 283500 | L22: =K22*0.63 -> 178605 | M22: =K22-L22 -> 104895
A23: ORD-1022 | B23: 45737 | C23: March | D23: Islamabad | E23: Furniture | F23: Study Chair | G23: Hira Baig | H23: 4 | I23: 12000 | J23: 5 | K23: =H23*I23*(1-J23/100) -> 45600 | L23: =K23*0.59 -> 26904 | M23: =K23-L23 -> 18696
A24: ORD-1023 | B24: 45689 | C24: February | D24: Rawalpindi | E24: Cosmetics | F24: Lipstick | G24: Nadia Aslam | H24: 8 | I24: 800 | J24: 0 | K24: =H24*I24*(1-J24/100) -> 6400 | L24: =K24*0.56 -> 3584 | M24: =K24-L24 -> 2816
A25: ORD-1024 | B25: 45718 | C25: March | D25: Karachi | E25: Clothing | F25: Shalwar Kameez | G25: Sana Iqbal | H25: 3 | I25: 2500 | J25: 20 | K25: =H25*I25*(1-J25/100) -> 6000 | L25: =K25*0.6 -> 3600 | M25: =K25-L25 -> 2400
A26: ORD-1025 | B26: 45732 | C26: March | D26: Karachi | E26: Cosmetics | F26: Lipstick | G26: Nadia Aslam | H26: 19 | I26: 800 | J26: 15 | K26: =H26*I26*(1-J26/100) -> 12920 | L26: =K26*0.6 -> 7752 | M26: =K26-L26 -> 5168
A27: ORD-1026 | B27: 45714 | C27: February | D27: Faisalabad | E27: Electronics | F27: Mobile Phone | G27: Fatima Khan | H27: 14 | I27: 45000 | J27: 10 | K27: =H27*I27*(1-J27/100) -> 567000 | L27: =K27*0.63 -> 357210 | M27: =K27-L27 -> 209790
A28: ORD-1027 | B28: 45716 | C28: February | D28: Lahore | E28: Clothing | F28: Shalwar Kameez | G28: Zain Hussain | H28: 11 | I28: 2500 | J28: 0 | K28: =H28*I28*(1-J28/100) -> 27500 | L28: =K28*0.6 -> 16500 | M28: =K28-L28 -> 11000
A29: ORD-1028 | B29: 45675 | C29: January | D29: Faisalabad | E29: Electronics | F29: Charger | G29: Usman Raza | H29: 9 | I29: 1500 | J29: 15 | K29: =H29*I29*(1-J29/100) -> 11475 | L29: =K29*0.6 -> 6885 | M29: =K29-L29 -> 4590
A30: ORD-1029 | B30: 45672 | C30: January | D30: Rawalpindi | E30: Clothing | F30: Shalwar Kameez | G30: Kamran Butt | H30: 1 | I30: 2500 | J30: 0 | K30: =H30*I30*(1-J30/100) -> 2500 | L30: =K30*0.74 -> 1850 | M30: =K30-L30 -> 650
A31: ORD-1030 | B31: 45663 | C31: January | D31: Faisalabad | E31: Furniture | F31: Bed Frame | G31: Ayesha Malik | H31: 13 | I31: 38000 | J31: 0 | K31: =H31*I31*(1-J31/100) -> 494000 | L31: =K31*0.58 -> 286520 | M31: =K31-L31 -> 207480
A32: ORD-1031 | B32: 45670 | C32: January | D32: Islamabad | E32: Furniture | F32: Wardrobe | G32: Zain Hussain | H32: 18 | I32: 62000 | J32: 15 | K32: =H32*I32*(1-J32/100) -> 948600 | L32: =K32*0.58 -> 550188 | M32: =K32-L32 -> 398412
A33: ORD-1032 | B33: 45695 | C33: February | D33: Lahore | E33: Cosmetics | F33: Face Wash | G33: Ahmed Ali | H33: 11 | I33: 450 | J33: 0 | K33: =H33*I33*(1-J33/100) -> 4950 | L33: =K33*0.56 -> 2772 | M33: =K33-L33 -> 2178
A34: ORD-1033 | B34: 45705 | C34: February | D34: Rawalpindi | E34: Electronics | F34: Mobile Phone | G34: Kamran Butt | H34: 3 | I34: 45000 | J34: 5 | K34: =H34*I34*(1-J34/100) -> 128250 | L34: =K34*0.56 -> 71820 | M34: =K34-L34 -> 56430
A35: ORD-1034 | B35: 45679 | C35: January | D35: Karachi | E35: Furniture | F35: Sofa Set | G35: Nadia Aslam | H35: 8 | I35: 85000 | J35: 20 | K35: =H35*I35*(1-J35/100) -> 544000 | L35: =K35*0.67 -> 364480 | M35: =K35-L35 -> 179520
A36: ORD-1035 | B36: 45719 | C36: March | D36: Faisalabad | E36: Cosmetics | F36: Face Wash | G36: Kamran Butt | H36: 11 | I36: 450 | J36: 10 | K36: =H36*I36*(1-J36/100) -> 4455 | L36: =K36*0.59 -> 2628.45 | M36: =K36-L36 -> 1826.55
A37: ORD-1036 | B37: 45727 | C37: March | D37: Karachi | E37: Groceries | F37: Cooking Oil | G37: Usman Raza | H37: 10 | I37: 650 | J37: 15 | K37: =H37*I37*(1-J37/100) -> 5525 | L37: =K37*0.61 -> 3370.25 | M37: =K37-L37 -> 2154.75
A38: ORD-1037 | B38: 45658 | C38: January | D38: Faisalabad | E38: Cosmetics | F38: Face Wash | G38: Fatima Khan | H38: 3 | I38: 450 | J38: 20 | K38: =H38*I38*(1-J38/100) -> 1080 | L38: =K38*0.59 -> 637.2 | M38: =K38-L38 -> 442.8
A39: ORD-1038 | B39: 45693 | C39: February | D39: Islamabad | E39: Clothing | F39: Kurta | G39: Sana Iqbal | H39: 10 | I39: 1800 | J39: 5 | K39: =H39*I39*(1-J39/100) -> 17100 | L39: =K39*0.64 -> 10944 | M39: =K39-L39 -> 6156
A40: ORD-1039 | B40: 45739 | C40: March | D40: Islamabad | E40: Cosmetics | F40: Face Wash | G40: Ahmed Ali | H40: 18 | I40: 450 | J40: 10 | K40: =H40*I40*(1-J40/100) -> 7290 | L40: =K40*0.74 -> 5394.6 | M40: =K40-L40 -> 1895.4
A41: ORD-1040 | B41: 45662 | C41: January | D41: Islamabad | E41: Clothing | F41: Shalwar Kameez | G41: Kamran Butt | H41: 5 | I41: 2500 | J41: 10 | K41: =H41*I41*(1-J41/100) -> 11250 | L41: =K41*0.61 -> 6862.5 | M41: =K41-L41 -> 4387.5
A42: ORD-1041 | B42: 45680 | C42: January | D42: Islamabad | E42: Electronics | F42: Headphones | G42: Kamran Butt | H42: 16 | I42: 8500 | J42: 10 | K42: =H42*I42*(1-J42/100) -> 122400 | L42: =K42*0.73 -> 89352 | M42: =K42-L42 -> 33048
A43: ORD-1042 | B43: 45660 | C43: January | D43: Faisalabad | E43: Groceries | F43: Basmati Rice | G43: Ahmed Ali | H43: 11 | I43: 350 | J43: 5 | K43: =H43*I43*(1-J43/100) -> 3657.5 | L43: =K43*0.68 -> 2487.1 | M43: =K43-L43 -> 1170.4
A44: ORD-1043 | B44: 45694 | C44: February | D44: Faisalabad | E44: Cosmetics | F44: Hair Oil | G44: Kamran Butt | H44: 1 | I44: 650 | J44: 0 | K44: =H44*I44*(1-J44/100) -> 650 | L44: =K44*0.57 -> 370.5 | M44: =K44-L44 -> 279.5
A45: ORD-1044 | B45: 45721 | C45: March | D45: Rawalpindi | E45: Clothing | F45: Jeans | G45: Nadia Aslam | H45: 18 | I45: 3200 | J45: 5 | K45: =H45*I45*(1-J45/100) -> 54720 | L45: =K45*0.64 -> 35020.8 | M45: =K45-L45 -> 19699.2
A46: ORD-1045 | B46: 45667 | C46: January | D46: Islamabad | E46: Clothing | F46: Jeans | G46: Ayesha Malik | H46: 8 | I46: 3200 | J46: 0 | K46: =H46*I46*(1-J46/100) -> 25600 | L46: =K46*0.62 -> 15872 | M46: =K46-L46 -> 9728
A47: ORD-1046 | B47: 45744 | C47: March | D47: Faisalabad | E47: Cosmetics | F47: Lipstick | G47: Ayesha Malik | H47: 6 | I47: 800 | J47: 5 | K47: =H47*I47*(1-J47/100) -> 4560 | L47: =K47*0.73 -> 3328.8 | M47: =K47-L47 -> 1231.2
A48: ORD-1047 | B48: 45663 | C48: January | D48: Islamabad | E48: Furniture | F48: Dining Table | G48: Bilal Sheikh | H48: 6 | I48: 45000 | J48: 0 | K48: =H48*I48*(1-J48/100) -> 270000 | L48: =K48*0.63 -> 170100 | M48: =K48-L48 -> 99900
A49: ORD-1048 | B49: 45685 | C49: January | D49: Faisalabad | E49: Electronics | F49: Laptop | G49: Hira Baig | H49: 12 | I49: 120000 | J49: 10 | K49: =H49*I49*(1-J49/100) -> 1296000 | L49: =K49*0.71 -> 920160 | M49: =K49-L49 -> 375840
A50: ORD-1049 | B50: 45665 | C50: January | D50: Lahore | E50: Electronics | F50: Charger | G50: Sana Iqbal | H50: 9 | I50: 1500 | J50: 0 | K50: =H50*I50*(1-J50/100) -> 13500 | L50: =K50*0.74 -> 9990 | M50: =K50-L50 -> 3510
A51: ORD-1050 | B51: 45700 | C51: February | D51: Rawalpindi | E51: Furniture | F51: Study Chair | G51: Sana Iqbal | H51: 1 | I51: 12000 | J51: 0 | K51: =H51*I51*(1-J51/100) -> 12000 | L51: =K51*0.73 -> 8760 | M51: =K51-L51 -> 3240
A52: ORD-1051 | B52: 45694 | C52: February | D52: Rawalpindi | E52: Groceries | F52: Basmati Rice | G52: Fatima Khan | H52: 20 | I52: 350 | J52: 15 | K52: =H52*I52*(1-J52/100) -> 5950 | L52: =K52*0.62 -> 3689 | M52: =K52-L52 -> 2261
A53: ORD-1052 | B53: 45702 | C53: February | D53: Rawalpindi | E53: Cosmetics | F53: Skin Cream | G53: Zain Hussain | H53: 19 | I53: 1200 | J53: 5 | K53: =H53*I53*(1-J53/100) -> 21660 | L53: =K53*0.6 -> 12996 | M53: =K53-L53 -> 8664
A54: ORD-1053 | B54: 45730 | C54: March | D54: Lahore | E54: Cosmetics | F54: Face Wash | G54: Ayesha Malik | H54: 12 | I54: 450 | J54: 15 | K54: =H54*I54*(1-J54/100) -> 4590 | L54: =K54*0.56 -> 2570.4 | M54: =K54-L54 -> 2019.6
A55: ORD-1054 | B55: 45727 | C55: March | D55: Rawalpindi | E55: Groceries | F55: Basmati Rice | G55: Bilal Sheikh | H55: 17 | I55: 350 | J55: 10 | K55: =H55*I55*(1-J55/100) -> 5355 | L55: =K55*0.68 -> 3641.4 | M55: =K55-L55 -> 1713.6
A56: ORD-1055 | B56: 45701 | C56: February | D56: Islamabad | E56: Cosmetics | F56: Lipstick | G56: Ayesha Malik | H56: 14 | I56: 800 | J56: 15 | K56: =H56*I56*(1-J56/100) -> 9520 | L56: =K56*0.69 -> 6568.8 | M56: =K56-L56 -> 2951.2
A57: ORD-1056 | B57: 45677 | C57: January | D57: Rawalpindi | E57: Groceries | F57: Cooking Oil | G57: Kamran Butt | H57: 1 | I57: 650 | J57: 10 | K57: =H57*I57*(1-J57/100) -> 585 | L57: =K57*0.61 -> 356.85 | M57: =K57-L57 -> 228.15
A58: ORD-1057 | B58: 45714 | C58: February | D58: Rawalpindi | E58: Cosmetics | F58: Foundation | G58: Hira Baig | H58: 15 | I58: 2200 | J58: 15 | K58: =H58*I58*(1-J58/100) -> 28050 | L58: =K58*0.69 -> 19354.5 | M58: =K58-L58 -> 8695.5
A59: ORD-1058 | B59: 45732 | C59: March | D59: Karachi | E59: Clothing | F59: Jeans | G59: Kamran Butt | H59: 20 | I59: 3200 | J59: 10 | K59: =H59*I59*(1-J59/100) -> 57600 | L59: =K59*0.57 -> 32832 | M59: =K59-L59 -> 24768
A60: ORD-1059 | B60: 45679 | C60: January | D60: Islamabad | E60: Electronics | F60: Laptop | G60: Usman Raza | H60: 1 | I60: 120000 | J60: 0 | K60: =H60*I60*(1-J60/100) -> 120000 | L60: =K60*0.6 -> 72000 | M60: =K60-L60 -> 48000
A61: ORD-1060 | B61: 45708 | C61: February | D61: Lahore | E61: Furniture | F61: Bed Frame | G61: Nadia Aslam | H61: 7 | I61: 38000 | J61: 15 | K61: =H61*I61*(1-J61/100) -> 226100 | L61: =K61*0.65 -> 146965 | M61: =K61-L61 -> 79135
A62: ORD-1061 | B62: 45662 | C62: January | D62: Lahore | E62: Clothing | F62: T-Shirt | G62: Ayesha Malik | H62: 6 | I62: 900 | J62: 20 | K62: =H62*I62*(1-J62/100) -> 4320 | L62: =K62*0.64 -> 2764.8 | M62: =K62-L62 -> 1555.2
A63: ORD-1062 | B63: 45724 | C63: March | D63: Lahore | E63: Furniture | F63: Dining Table | G63: Hira Baig | H63: 17 | I63: 45000 | J63: 20 | K63: =H63*I63*(1-J63/100) -> 612000 | L63: =K63*0.67 -> 410040 | M63: =K63-L63 -> 201960
A64: ORD-1063 | B64: 45708 | C64: February | D64: Rawalpindi | E64: Furniture | F64: Study Chair | G64: Hira Baig | H64: 6 | I64: 12000 | J64: 15 | K64: =H64*I64*(1-J64/100) -> 61200 | L64: =K64*0.64 -> 39168 | M64: =K64-L64 -> 22032
A65: ORD-1064 | B65: 45684 | C65: January | D65: Islamabad | E65: Cosmetics | F65: Hair Oil | G65: Ayesha Malik | H65: 9 | I65: 650 | J65: 15 | K65: =H65*I65*(1-J65/100) -> 4972.5 | L65: =K65*0.57 -> 2834.325 | M65: =K65-L65 -> 2138.175
A66: ORD-1065 | B66: 45696 | C66: February | D66: Islamabad | E66: Groceries | F66: Flour (Aata) | G66: Kamran Butt | H66: 3 | I66: 280 | J66: 5 | K66: =H66*I66*(1-J66/100) -> 798 | L66: =K66*0.58 -> 462.84 | M66: =K66-L66 -> 335.16
A67: ORD-1066 | B67: 45711 | C67: February | D67: Karachi | E67: Electronics | F67: Mobile Phone | G67: Zain Hussain | H67: 14 | I67: 45000 | J67: 10 | K67: =H67*I67*(1-J67/100) -> 567000 | L67: =K67*0.66 -> 374220 | M67: =K67-L67 -> 192780
A68: ORD-1067 | B68: 45690 | C68: February | D68: Karachi | E68: Furniture | F68: Bed Frame | G68: Nadia Aslam | H68: 1 | I68: 38000 | J68: 20 | K68: =H68*I68*(1-J68/100) -> 30400 | L68: =K68*0.63 -> 19152 | M68: =K68-L68 -> 11248
A69: ORD-1068 | B69: 45669 | C69: January | D69: Islamabad | E69: Furniture | F69: Bed Frame | G69: Kamran Butt | H69: 18 | I69: 38000 | J69: 20 | K69: =H69*I69*(1-J69/100) -> 547200 | L69: =K69*0.73 -> 399456 | M69: =K69-L69 -> 147744
A70: ORD-1069 | B70: 45696 | C70: February | D70: Islamabad | E70: Furniture | F70: Bed Frame | G70: Ahmed Ali | H70: 13 | I70: 38000 | J70: 10 | K70: =H70*I70*(1-J70/100) -> 444600 | L70: =K70*0.68 -> 302328 | M70: =K70-L70 -> 142272
A71: ORD-1070 | B71: 45712 | C71: February | D71: Karachi | E71: Furniture | F71: Dining Table | G71: Nadia Aslam | H71: 18 | I71: 45000 | J71: 0 | K71: =H71*I71*(1-J71/100) -> 810000 | L71: =K71*0.73 -> 591300 | M71: =K71-L71 -> 218700
A72: ORD-1071 | B72: 45735 | C72: March | D72: Lahore | E72: Clothing | F72: T-Shirt | G72: Usman Raza | H72: 15 | I72: 900 | J72: 5 | K72: =H72*I72*(1-J72/100) -> 12825 | L72: =K72*0.56 -> 7182 | M72: =K72-L72 -> 5643
A73: ORD-1072 | B73: 45699 | C73: February | D73: Karachi | E73: Furniture | F73: Wardrobe | G73: Sana Iqbal | H73: 13 | I73: 62000 | J73: 10 | K73: =H73*I73*(1-J73/100) -> 725400 | L73: =K73*0.7 -> 507780 | M73: =K73-L73 -> 217620
A74: ORD-1073 | B74: 45697 | C74: February | D74: Lahore | E74: Furniture | F74: Sofa Set | G74: Kamran Butt | H74: 2 | I74: 85000 | J74: 10 | K74: =H74*I74*(1-J74/100) -> 153000 | L74: =K74*0.59 -> 90270 | M74: =K74-L74 -> 62730
A75: ORD-1074 | B75: 45682 | C75: January | D75: Lahore | E75: Clothing | F75: Kurta | G75: Ayesha Malik | H75: 1 | I75: 1800 | J75: 20 | K75: =H75*I75*(1-J75/100) -> 1440 | L75: =K75*0.58 -> 835.2 | M75: =K75-L75 -> 604.8
A76: ORD-1075 | B76: 45673 | C76: January | D76: Lahore | E76: Cosmetics | F76: Lipstick | G76: Hira Baig | H76: 9 | I76: 800 | J76: 10 | K76: =H76*I76*(1-J76/100) -> 6480 | L76: =K76*0.58 -> 3758.4 | M76: =K76-L76 -> 2721.6
A77: ORD-1076 | B77: 45740 | C77: March | D77: Lahore | E77: Electronics | F77: Headphones | G77: Fatima Khan | H77: 19 | I77: 8500 | J77: 0 | K77: =H77*I77*(1-J77/100) -> 161500 | L77: =K77*0.74 -> 119510 | M77: =K77-L77 -> 41990
A78: ORD-1077 | B78: 45738 | C78: March | D78: Faisalabad | E78: Furniture | F78: Dining Table | G78: Fatima Khan | H78: 19 | I78: 45000 | J78: 5 | K78: =H78*I78*(1-J78/100) -> 812250 | L78: =K78*0.57 -> 462982.5 | M78: =K78-L78 -> 349267.5
A79: ORD-1078 | B79: 45716 | C79: February | D79: Rawalpindi | E79: Clothing | F79: Dupatta | G79: Ahmed Ali | H79: 12 | I79: 700 | J79: 20 | K79: =H79*I79*(1-J79/100) -> 6720 | L79: =K79*0.64 -> 4300.8 | M79: =K79-L79 -> 2419.2
A80: ORD-1079 | B80: 45691 | C80: February | D80: Rawalpindi | E80: Groceries | F80: Basmati Rice | G80: Zain Hussain | H80: 16 | I80: 350 | J80: 0 | K80: =H80*I80*(1-J80/100) -> 5600 | L80: =K80*0.64 -> 3584 | M80: =K80-L80 -> 2016
A81: ORD-1080 | B81: 45709 | C81: February | D81: Faisalabad | E81: Electronics | F81: Charger | G81: Usman Raza | H81: 17 | I81: 1500 | J81: 10 | K81: =H81*I81*(1-J81/100) -> 22950 | L81: =K81*0.67 -> 15376.5 | M81: =K81-L81 -> 7573.5
A82: ORD-1081 | B82: 45741 | C82: March | D82: Faisalabad | E82: Furniture | F82: Bed Frame | G82: Nadia Aslam | H82: 9 | I82: 38000 | J82: 10 | K82: =H82*I82*(1-J82/100) -> 307800 | L82: =K82*0.72 -> 221616 | M82: =K82-L82 -> 86184
A83: ORD-1082 | B83: 45666 | C83: January | D83: Faisalabad | E83: Electronics | F83: Charger | G83: Nadia Aslam | H83: 20 | I83: 1500 | J83: 15 | K83: =H83*I83*(1-J83/100) -> 25500 | L83: =K83*0.62 -> 15810 | M83: =K83-L83 -> 9690
A84: ORD-1083 | B84: 45716 | C84: February | D84: Islamabad | E84: Electronics | F84: Charger | G84: Ayesha Malik | H84: 12 | I84: 1500 | J84: 10 | K84: =H84*I84*(1-J84/100) -> 16200 | L84: =K84*0.62 -> 10044 | M84: =K84-L84 -> 6156
A85: ORD-1084 | B85: 45739 | C85: March | D85: Islamabad | E85: Cosmetics | F85: Skin Cream | G85: Kamran Butt | H85: 7 | I85: 1200 | J85: 0 | K85: =H85*I85*(1-J85/100) -> 8400 | L85: =K85*0.6 -> 5040 | M85: =K85-L85 -> 3360
A86: ORD-1085 | B86: 45704 | C86: February | D86: Rawalpindi | E86: Electronics | F86: Charger | G86: Hira Baig | H86: 15 | I86: 1500 | J86: 0 | K86: =H86*I86*(1-J86/100) -> 22500 | L86: =K86*0.57 -> 12825 | M86: =K86-L86 -> 9675
A87: ORD-1086 | B87: 45670 | C87: January | D87: Karachi | E87: Groceries | F87: Sugar | G87: Sana Iqbal | H87: 16 | I87: 200 | J87: 20 | K87: =H87*I87*(1-J87/100) -> 2560 | L87: =K87*0.66 -> 1689.6 | M87: =K87-L87 -> 870.4
A88: ORD-1087 | B88: 45712 | C88: February | D88: Rawalpindi | E88: Groceries | F88: Flour (Aata) | G88: Hira Baig | H88: 9 | I88: 280 | J88: 10 | K88: =H88*I88*(1-J88/100) -> 2268 | L88: =K88*0.6 -> 1360.8 | M88: =K88-L88 -> 907.2
A89: ORD-1088 | B89: 45681 | C89: January | D89: Karachi | E89: Groceries | F89: Basmati Rice | G89: Kamran Butt | H89: 6 | I89: 350 | J89: 5 | K89: =H89*I89*(1-J89/100) -> 1995 | L89: =K89*0.59 -> 1177.05 | M89: =K89-L89 -> 817.95
A90: ORD-1089 | B90: 45697 | C90: February | D90: Rawalpindi | E90: Cosmetics | F90: Face Wash | G90: Bilal Sheikh | H90: 4 | I90: 450 | J90: 5 | K90: =H90*I90*(1-J90/100) -> 1710 | L90: =K90*0.61 -> 1043.1 | M90: =K90-L90 -> 666.9
A91: ORD-1090 | B91: 45694 | C91: February | D91: Islamabad | E91: Clothing | F91: Dupatta | G91: Usman Raza | H91: 9 | I91: 700 | J91: 0 | K91: =H91*I91*(1-J91/100) -> 6300 | L91: =K91*0.74 -> 4662 | M91: =K91-L91 -> 1638
A92: ORD-1091 | B92: 45726 | C92: March | D92: Karachi | E92: Furniture | F92: Sofa Set | G92: Ahmed Ali | H92: 19 | I92: 85000 | J92: 10 | K92: =H92*I92*(1-J92/100) -> 1453500 | L92: =K92*0.64 -> 930240 | M92: =K92-L92 -> 523260
A93: ORD-1092 | B93: 45699 | C93: February | D93: Karachi | E93: Clothing | F93: Jeans | G93: Hira Baig | H93: 4 | I93: 3200 | J93: 0 | K93: =H93*I93*(1-J93/100) -> 12800 | L93: =K93*0.63 -> 8064 | M93: =K93-L93 -> 4736
A94: ORD-1093 | B94: 45676 | C94: January | D94: Lahore | E94: Electronics | F94: Laptop | G94: Nadia Aslam | H94: 10 | I94: 120000 | J94: 0 | K94: =H94*I94*(1-J94/100) -> 1200000 | L94: =K94*0.75 -> 900000 | M94: =K94-L94 -> 300000
A95: ORD-1094 | B95: 45675 | C95: January | D95: Faisalabad | E95: Cosmetics | F95: Face Wash | G95: Nadia Aslam | H95: 8 | I95: 450 | J95: 20 | K95: =H95*I95*(1-J95/100) -> 2880 | L95: =K95*0.63 -> 1814.4 | M95: =K95-L95 -> 1065.6
A96: ORD-1095 | B96: 45698 | C96: February | D96: Rawalpindi | E96: Furniture | F96: Wardrobe | G96: Nadia Aslam | H96: 20 | I96: 62000 | J96: 0 | K96: =H96*I96*(1-J96/100) -> 1240000 | L96: =K96*0.67 -> 830800 | M96: =K96-L96 -> 409200
A97: ORD-1096 | B97: 45720 | C97: March | D97: Karachi | E97: Electronics | F97: Headphones | G97: Fatima Khan | H97: 6 | I97: 8500 | J97: 5 | K97: =H97*I97*(1-J97/100) -> 48450 | L97: =K97*0.58 -> 28101 | M97: =K97-L97 -> 20349
A98: ORD-1097 | B98: 45663 | C98: January | D98: Lahore | E98: Furniture | F98: Bed Frame | G98: Nadia Aslam | H98: 16 | I98: 38000 | J98: 10 | K98: =H98*I98*(1-J98/100) -> 547200 | L98: =K98*0.56 -> 306432 | M98: =K98-L98 -> 240768
A99: ORD-1098 | B99: 45711 | C99: February | D99: Islamabad | E99: Furniture | F99: Sofa Set | G99: Ayesha Malik | H99: 9 | I99: 85000 | J99: 20 | K99: =H99*I99*(1-J99/100) -> 612000 | L99: =K99*0.68 -> 416160 | M99: =K99-L99 -> 195840
A100: ORD-1099 | B100: 45671 | C100: January | D100: Lahore | E100: Cosmetics | F100: Lipstick | G100: Usman Raza | H100: 9 | I100: 800 | J100: 5 | K100: =H100*I100*(1-J100/100) -> 6840 | L100: =K100*0.56 -> 3830.4 | M100: =K100-L100 -> 3009.6
...

Sheet Summary
B2: 🛍️ Pakistan Retail Sales — Q1 2025 Summary
B4: Revenue by Category (PKR) | F4: Revenue by City (PKR)
B5: Category | C5: Total Revenue | D5: % Share | F5: City | G5: Total Revenue | H5: Total Profit
B6: Clothing | C6: =SUMIF(Sales_Data!E:E,B6,Sales_Data!K:K) -> 672905 | D6: =C6/SUM(C6:C10) -> 0.019850529 | F6: Lahore | G6: =SUMIF(Sales_Data!D:D,F6,Sales_Data!K:K) -> 7122941 | H6: =SUMIF(Sales_Data!D:D,F6,Sales_Data!M:M) -> 2512878.2
B7: Electronics | C7: =SUMIF(Sales_Data!E:E,B7,Sales_Data!K:K) -> 15241750 | D7: =C7/SUM(C6:C10) -> 0.44962782 | F7: Karachi | G7: =SUMIF(Sales_Data!D:D,F7,Sales_Data!K:K) -> 7673557.5 | H7: =SUMIF(Sales_Data!D:D,F7,Sales_Data!M:M) -> 2555583.5
B8: Groceries | C8: =SUMIF(Sales_Data!E:E,B8,Sales_Data!K:K) -> 195037 | D8: =C8/SUM(C6:C10) -> 0.0057535428 | F8: Islamabad | G8: =SUMIF(Sales_Data!D:D,F8,Sales_Data!K:K) -> 7542968 | H8: =SUMIF(Sales_Data!D:D,F8,Sales_Data!M:M) -> 2672484.8
B9: Furniture | C9: =SUMIF(Sales_Data!E:E,B9,Sales_Data!K:K) -> 17343700 | D9: =C9/SUM(C6:C10) -> 0.51163482 | F9: Faisalabad | G9: =SUMIF(Sales_Data!D:D,F9,Sales_Data!K:K) -> 4927067.5 | H9: =SUMIF(Sales_Data!D:D,F9,Sales_Data!M:M) -> 1783135.4
B10: Cosmetics | C10: =SUMIF(Sales_Data!E:E,B10,Sales_Data!K:K) -> 445200 | D10: =C10/SUM(C6:C10) -> 0.013133289 | F10: Rawalpindi | G10: =SUMIF(Sales_Data!D:D,F10,Sales_Data!K:K) -> 6632058 | H10: =SUMIF(Sales_Data!D:D,F10,Sales_Data!M:M) -> 2444508.6
B11: TOTAL | C11: =SUM(C6:C10) -> 33898592
B13: Monthly Revenue
B14: Month | C14: Revenue | D14: Profit
B15: January | C15: =SUMIF(Sales_Data!C:C,B15,Sales_Data!K:K) -> 15111715 | D15: =SUMIF(Sales_Data!C:C,B15,Sales_Data!M:M) -> 5371570.8
B16: February | C16: =SUMIF(Sales_Data!C:C,B16,Sales_Data!K:K) -> 9574198.5 | D16: =SUMIF(Sales_Data!C:C,B16,Sales_Data!M:M) -> 3382188.2
B17: March | C17: =SUMIF(Sales_Data!C:C,B17,Sales_Data!K:K) -> 9212678.5 | D17: =SUMIF(Sales_Data!C:C,B17,Sales_Data!M:M) -> 3214831.5

Sheet Practice_Functions
B2: 📊 Excel Functions Practice Sheet
B4: INSTRUCTIONS: Try to write these formulas yourself in column E. Answers are in column F.
B6: Function | C6: Task | D6: Your Answer → | F6: Formula to Use
B7: SUMIF | C7: Total Revenue from Lahore | D7: ← Write here | F7: =SUMIF(Sales_Data!D:D,"Lahore",Sales_Data!K:K) -> 7122941
B8: COUNTIF | C8: Count orders in Clothing category | D8: ← Write here | F8: =COUNTIF(Sales_Data!E:E,"Clothing") -> 39
B9: AVERAGEIF | C9: Average profit for Electronics | D9: ← Write here | F9: =AVERAGEIF(Sales_Data!E:E,"Electronics",Sales_Data!M:M) -> 128672.04
B10: SUMIFS | C10: Total revenue from Karachi + Clothing | D10: ← Write here | F10: =SUMIFS(Sales_Data!K:K,Sales_Data!D:D,"Karachi",Sales_Data!E:E,"Clothing") -> 147650
B11: VLOOKUP | C11: Find Unit Price for 'Laptop' | D11: ← Write here | F11: =VLOOKUP("Laptop",Sales_Data!F:I,4,0) -> 120000
B12: MAX | C12: Highest single order revenue | D12: ← Write here | F12: =MAX(Sales_Data!K:K) -> 2400000
B13: MIN | C13: Lowest single order revenue | D13: ← Write here | F13: =MIN(Sales_Data!K:K) -> 510
B14: AVERAGE | C14: Average order revenue | D14: ← Write here | F14: =AVERAGE(Sales_Data!K:K) -> 169492.96
B15: IF | C15: Flag profit > 10000 as 'High' else 'Low' | D15: ← Write here | F15: =IF(Sales_Data!M2>10000,"High","Low") -> Low
B16: COUNTA | C16: Count total orders | D16: ← Write here | F16: =COUNTA(Sales_Data!A:A)-1 -> 200
